skfolio/__init__.py
skfolio/_constants.py
skfolio/exceptions.py
skfolio/typing.py
skfolio/cluster/__init__.py
skfolio/cluster/_hierarchical.py
skfolio/datasets/__init__.py
skfolio/datasets/_base.py
skfolio/datasets/data/__init__.py
skfolio/datasets/data/factors_dataset.csv.gz
skfolio/datasets/data/sp500_dataset.csv.gz
skfolio/datasets/data/sp500_index.csv.gz
skfolio/distance/__init__.py
skfolio/distance/_base.py
skfolio/distance/_distance.py
skfolio/distribution/__init__.py
skfolio/distribution/_base.py
skfolio/distribution/copula/__init__.py
skfolio/distribution/copula/_base.py
skfolio/distribution/copula/_clayton.py
skfolio/distribution/copula/_gaussian.py
skfolio/distribution/copula/_gumbel.py
skfolio/distribution/copula/_independent.py
skfolio/distribution/copula/_joe.py
skfolio/distribution/copula/_selection.py
skfolio/distribution/copula/_student_t.py
skfolio/distribution/copula/_utils.py
skfolio/distribution/multivariate/__init__.py
skfolio/distribution/multivariate/_base.py
skfolio/distribution/multivariate/_utils.py
skfolio/distribution/multivariate/_vine_copula.py
skfolio/distribution/univariate/__init__.py
skfolio/distribution/univariate/_base.py
skfolio/distribution/univariate/_gaussian.py
skfolio/distribution/univariate/_johnson_su.py
skfolio/distribution/univariate/_normal_inverse_gaussian.py
skfolio/distribution/univariate/_selection.py
skfolio/distribution/univariate/_student_t.py
skfolio/measures/__init__.py
skfolio/measures/_enums.py
skfolio/measures/_measures.py
skfolio/metrics/__init__.py
skfolio/metrics/_scorer.py
skfolio/model_selection/__init__.py
skfolio/model_selection/_combinatorial.py
skfolio/model_selection/_multiple_randomized_cv.py
skfolio/model_selection/_validation.py
skfolio/model_selection/_walk_forward.py
skfolio/moments/__init__.py
skfolio/moments/covariance/__init__.py
skfolio/moments/covariance/_base.py
skfolio/moments/covariance/_denoise_covariance.py
skfolio/moments/covariance/_detone_covariance.py
skfolio-0.15.3.dist-info/licenses/LICENSE
skfolio-0.15.3.dist-info/METADATA
skfolio-0.15.3.dist-info/WHEEL
skfolio-0.15.3.dist-info/top_level.txt
skfolio-0.15.3.dist-info/RECORD
