Metadata-Version: 2.4
Name: skfolio
Version: 0.15.3
Summary: Portfolio optimization built on top of scikit-learn
Author-email: Hugo Delatte <delatte.hugo@gmail.com>
Maintainer-email: Hugo Delatte <delatte.hugo@gmail.com>, Matteo Manzi <matteomanzi09@gmail.com>, Carlo Nicolini <c.nicolini@ipazia.com>
License: BSD 3-Clause License
Project-URL: API Reference, https://www.skfolio.org/api_reference.html
Project-URL: Documentation, https://www.skfolio.org
Project-URL: Tutorials, https://www.skfolio.org
Project-URL: Repository, https://github.com/skfolio/skfolio
Keywords: portfolio,optimization,optimisation,finance,asset,allocation,quantitative,quant,investment,strategy,machine-learning,scikit-learn,data-mining,data-science
Classifier: Intended Audience :: Developers
Classifier: Intended Audience :: Science/Research
Classifier: Intended Audience :: Financial and Insurance Industry
Classifier: License :: OSI Approved :: BSD License
Classifier: Operating System :: Unix
Classifier: Operating System :: Microsoft :: Windows
Classifier: Operating System :: MacOS
Classifier: Programming Language :: Python
Classifier: Programming Language :: Python :: 3
Classifier: Programming Language :: Python :: 3.10
Classifier: Programming Language :: Python :: 3.11
Classifier: Programming Language :: Python :: 3.12
Classifier: Topic :: Scientific/Engineering :: Mathematics
Classifier: Topic :: Office/Business :: Financial :: Investment
Classifier: Topic :: Software Development
Requires-Python: >=3.10
License-File: LICENSE
Requires-Dist: numpy>=1.23.4
Requires-Dist: scipy>=1.15.2
Requires-Dist: pandas>=1.4.1
Requires-Dist: cvxpy-base>=1.5.0
Requires-Dist: clarabel>=0.9.0
Requires-Dist: scikit-learn>=1.6.0
Requires-Dist: joblib>=1.3.2
Requires-Dist: plotly>=5.22.0
Provides-Extra: dev
Requires-Dist: PySCIPOpt<6.0.0; extra == "dev"
Requires-Dist: pytest; extra == "dev"
Requires-Dist: pytest-cov; extra == "dev"
Requires-Dist: ruff; extra == "dev"
Requires-Dist: pre-commit; extra == "dev"
Provides-Extra: docs
Requires-Dist: PySCIPOpt<6.0.0; extra == "docs"
Requires-Dist: Sphinx; extra == "docs"
Requires-Dist: sphinx-gallery; extra == "docs"
Requires-Dist: pydata-sphinx-theme~=0.16; extra == "docs"
Requires-Dist: matplotlib; extra == "docs"
Requires-Dist: kaleido; extra == "docs"
Requires-Dist: sphinx-copybutton; extra == "docs"
Requires-Dist: numpydoc; extra == "docs"
Requires-Dist: sphinx-favicon; extra == "docs"
Requires-Dist: sphinxext.opengraph; extra == "docs"
Requires-Dist: sphinx-sitemap; extra == "docs"
Requires-Dist: jupyterlite-sphinx; extra == "docs"
Requires-Dist: jupyterlite-pyodide-kernel; extra == "docs"
Requires-Dist: nbformat; extra == "docs"
Requires-Dist: sphinx-last-updated-by-git; extra == "docs"
Dynamic: license-file
